Workbook

Sheet Malzeme Listesi
A1: SAP-Nr. | B1: SAP - Bezeichnung/Description | C1: Material Type | E1: Service -bezeichnung/description
A2: 1 | B2: small material | D2: Disabled
A3: 15 | B3: plain washer DIN125 A10,5 A2 | C3: ROH | E3: 1 PAK = 50 ST
A4: 16 | B4: plain washer DIN125 A10,5 300HV tZn | C4: ROH | D4: Disabled | E4: replaced by SAP 24283
A5: 17 | B5: plain washer DIN125 A13 A2 | C5: ROH | E5: 1 PAK = 25 ST
A6: 18 | B6: plain washer DIN125 A13 brass | C6: ROH
A7: 19 | B7: plain washer DIN125 A13 300HV tZn | C7: ROH | D7: Disabled | E7: replaced by SAP 23807
A8: 20 | B8: plain washer DIN125 A17 A2 | C8: ROH | E8: 1 PAK = 25 ST
A9: 21 | B9: plain washer DIN125 A17,0 HDG | C9: ROH | D9: Disabled | E9: replaced by SAP 24285
A10: 25 | B10: plain washer DIN125 A06,4 tZn | C10: ROH
A11: 26 | B11: plain washer DIN125 A08,4 A2 | C11: ROH | E11: 1 PAK = 50 ST
A12: 29 | B12: spring washer DIN127 B10 1.4310 | C12: ROH | D12: Disabled | E12: replaced by SAP 3095
A13: 30 | B13: spring washer DIN127 B10 tZn | C13: ROH | E13: 1 PAK = 50 ST
A14: 31 | B14: spring washer DIN127 B12 A2 1.4310 | C14: ROH
A15: 32 | B15: spring washer DIN127 B12 tZn | C15: ROH
A16: 33 | B16: washer, spring lock DIN127 B04 1.4310 | C16: ROH | D16: Disabled | E16: replaced by SAP 3096
A17: 35 | B17: washer, spring lock DIN127 B06 1.4310 | C17: ROH | D17: Disabled | E17: replaced by SAP 3098
A18: 36 | B18: spring washer DIN127 B06 tZn | C18: ROH | D18: Disabled | E18: replaced by SAP 1016
A19: 37 | B19: spring washer DIN127 B08 1.4310 | C19: ROH | D19: Disabled | E19: replaced by SAP 3102
A20: 38 | B20: washer, spring lock- DIN127 B08 tZn | C20: ROH
A21: 42 | B21: domed cap nut DIN1587 M08 A2 | C21: ROH
A22: 43 | B22: headed drill bushes DIN172 A 45x67mm | C22: ROH | E22: for the shear pin 3601113-2 (SAP 1161).
A23: 45 | B23: circlip for shafts DIN471 45x1,75 | C23: ROH | E23: circlip for shear pin
A24: 47 | B24: lifting eye bolt DIN580 M10 tZn | C24: ROH
A25: 48 | B25: lifting eye bolt DIN580 M20 tZn | C25: ROH
A26: 49 | B26: lifting eye bolt DIN580 M08 A2 | C26: ROH | D26: Disabled | E26: replaced by: SAP 582545
A27: 50 | B27: lifting eye bolt DIN580 M08 HDG | C27: ROH
A28: 51 | B28: lifting eye nut DIN582 M12 A2 | C28: ROH
A29: 53 | B29: mushroom head screw DIN603 M05x020 A2 | C29: ROH
A30: 55 | B30: mushroom head screw DIN603 M06x030 A2 | C30: ROH
A31: 56 | B31: mushroom head screw DIN603 M06x050 A2 | C31: ROH
A32: 57 | B32: mushroom head screw DIN603 M08x060 A2 | C32: ROH
A33: 58 | B33: lock washer DIN6797 A12,5 A2 | C33: ROH
A34: 59 | B34: HT-bolt DIN6914 M12x055 tZn | C34: ROH
A35: 60 | B35: HT-bolt DIN6914 M12x060 tZn | C35: ROH
A36: 61 | B36: HT-bolt DIN6914 M12x065 tZn | C36: ROH
A37: 62 | B37: HT-bolt DIN6914 M16x090 tZn | C37: ROH
A38: 63 | B38: HT-bolt DIN6914 M24x160 tZn | C38: ROH
A39: 65 | B39: HT-nut DIN6915 M12 10 tZn | C39: ROH | E39: 1 PAK = 25 ST
A40: 67 | B40: HV-plain washer DIN6916 13 tZn | C40: ROH | E40: 1 PAK = 25 ST
A41: 68 | B41: HT-washer DIN6916 17 tZn | C41: ROH | E41: 1 PAK = 25 ST
A42: 69 | B42: HT-washer DIN6916 21 tZn | C42: ROH | E42: 1 PAK = 25 ST
A43: 72 | B43: lubrication nipple DIN71412 AR1/4" galZn | C43: ROH
A44: 73 | B44: blind rivet DIN7337 3x6 A alu/A2 | C44: ROH | E44: 1 PAK = 50 ST
A45: 74 | B45: blind rivet DIN7337 4x10 alu/A2 | C45: ROH | E45: 1 PAK = 50 ST
A46: 76 | B46: c-sunk screw,hex.soc DIN7991 M06x020 8.8 | C46: ROH
A47: 78 | B47: cylinder head screw DIN84 M04x025 A2 | C47: ROH
A48: 80 | B48: plain washer large DIN9021 13 tZn | C48: ROH | E48: large diameter washer, 1 PAK = 25 ST
A49: 81 | B49: plain washer large DIN9021 06,4 A2 | C49: ROH | E49: large diameter washer, 1 PAK = 50 ST
A50: 83 | B50: plain washer, large DIN9021 08,4 tZn | C50: ROH | E50: large diameter washer, 1 PAK = 50 ST
A51: 84 | B51: cylinder head screw ISO4762 M06x030 A2 | C51: ROH
A52: 86 | B52: hexagon head screw DIN931 M12x120 8.8tZn | C52: ROH
A53: 87 | B53: hexagon head screw DIN931 M12x040 A2 | C53: ROH
A54: 88 | B54: hexagon head screw DIN931 M12x045 A2 | C54: ROH
A55: 89 | B55: hexagon head screw DIN931 M12x045 8.8tZn | C55: ROH
A56: 90 | B56: hexagon head screw DIN931 M12x055 8.8tZn | C56: ROH
A57: 91 | B57: hexagon bolt DIN931 M16x210 10.9HDG | C57: ROH
A58: 92 | B58: hexagon head screw DIN931 M16x050 10.9tZ | C58: ROH | D58: Disabled | E58: replaced by SAP 13613
A59: 93 | B59: hexagon head screw DIN931 M16x055 8.8tZn | C59: ROH
A60: 94 | B60: hexagon head screw DIN931 M16x060 10.9tZ | C60: ROH
A61: 95 | B61: hexagon head screw DIN931 M16x065 10.9tZ | C61: ROH
A62: 96 | B62: hexagon head screw DIN931 M16x070 8.8tZn | C62: ROH
A63: 97 | B63: hexagon head screw DIN931 M20x050 10.9tZ | C63: ROH
A64: 98 | B64: hexagon head screw DIN931 M24x140 10.9 | C64: ROH | D64: Disabled | E64: replaced by SAP 31727
A65: 99 | B65: hexagon head screw DIN931 M24x170 10.9 | C65: ROH
A66: 100 | B66: hexagon head screw DIN933 M10x025 8.8tZn | C66: ROH
A67: 101 | B67: hexagon head screw DIN933 M10x045 8.8tZn | C67: ROH
A68: 102 | B68: hexagon head screw DIN933 M10x050 A2 | C68: ROH
A69: 103 | B69: hexagon head screw DIN933 M10x050 8.8tZn | C69: ROH
A70: 106 | B70: hexagon head screw DIN933 M12x025 A2 | C70: ROH
A71: 107 | B71: hexagon head screw DIN933 M12x030 8.8tZn | C71: ROH | E71: 1 PAK = 25 ST
A72: 108 | B72: hexagon head screw DIN933 M12x035 8.8tZn | C72: ROH
A73: 109 | B73: hexagon head screw DIN933 M12x040 A2 | C73: ROH
A74: 110 | B74: hexagon head screw DIN933 M12x045 8.8tZn | C74: ROH
A75: 111 | B75: hexagon head screw DIN933 M12x050 8.8tZn | C75: ROH | E75: 1 PAK = 25 ST
A76: 112 | B76: hexagon head screw DIN933 M12x065 8.8tZn | C76: ROH
A77: 113 | B77: hexagon head screw DIN933 M12x080 8.8tZn | C77: ROH
A78: 114 | B78: hexagon head scr. ISO4017 M16x020 8.8tZn | C78: ROH
A79: 115 | B79: spring washer DIN128 B12 tZn | C79: ROH
A80: 117 | B80: parallel pin DIN7979 16m6x050 | C80: ROH
A81: 118 | B81: hexagon head screw ISO4014M16x040 A2 | C81: ROH
A82: 119 | B82: hexagon bolt ISO4017 M05x016 A2 | C82: ROH | E82: replaced by : SAP 3168
A83: 120 | B83: hexagon head scr. ISO4017 M06x025 A2 | C83: ROH | E83: 1 PAK = 50 ST
A84: 121 | B84: hexagon head screw DIN933 M06x030 8.8tZn | C84: ROH
A85: 122 | B85: hexagon head scr. ISO4017 M08x016 A2 | C85: ROH | D85: Disabled | E85: replaced by SAP 1758
A86: 123 | B86: hexagon head scr. ISO4017 M08x020 A2 | C86: ROH | E86: 1 PAK = 25 ST
A87: 124 | B87: hexagon bolt ISO4017 M08x020 8.8HDG | C87: PC | D87: 0.1
A88: 125 | B88: hexagon head screw DIN933 M08x025 A2 | C88: ROH | E88: 1 PAK = 25 ST
A89: 126 | B89: hexagon head screw DIN933 M08x025 8.8tZn | C89: ROH | E89: 1 PAK = 25 ST
A90: 127 | B90: hexagon head screw DIN933 M08x030 A2 | C90: ROH | E90: 1 PAK = 25 ST
A91: 128 | B91: hexagon head screw DIN933 M08x030 8.8tZn | C91: ROH
A92: 129 | B92: hexagon head screw DIN933 M08x035 A2 | C92: ROH
A93: 130 | B93: hexagon head screw DIN933 M08x035 tZn | C93: ROH
A94: 131 | B94: hexagon head screw DIN933 M08x040 A2 | C94: ROH | E94: 1 PAK = 25 ST
A95: 132 | B95: hexagon head screw DIN933 M08x045 tZn | C95: ROH
A96: 133 | B96: hexagon head screw DIN933 M08x050 A2 | C96: ROH | E96: 1 PAK = 25 ST
A97: 134 | B97: hexagon head screw DIN933 M08x060 8.8tZn | C97: ROH
A98: 135 | B98: hexagon nut DIN934 M10 A2 | C98: ROH | E98: 1 PAK = 25 ST
A99: 136 | B99: hexagon nut DIN934 M10 8tZn | C99: ROH | D99: Disabled | E99: replaced by SAP 78628; 1 PAK = 25 ST
A100: 137 | B100: hexagon nut DIN934 M12 A2 | C100: ROH | E100: 1 PAK = 25 ST
...

Sheet Sap No Değişiklikleri
A2: eski sap no | B2: eski sap no ürün adı | D2: yeni sap no | E2: yeni sap no ürün adı
A3: 45247 | B3: =VLOOKUP(A3,[1]list!A:C,2,0) -> PCB CAN optical distribution V2.0 | D3: 651958 | E3: =VLOOKUP(D3,'Malzeme Listesi'!A:C,2,0) -> PCB CAN optical distribut. cabinet V2.1
A4: 47416 | B4: =VLOOKUP(A4,[1]list!A:C,2,0) -> PCB scada-interface V1.1 type F4 | D4: 47496 | E4: =VLOOKUP(D4,'Malzeme Listesi'!A:C,2,0) -> PCB scada-interface V1.1 type F4R
A5: 50081 | B5: =VLOOKUP(A5,[1]list!A:C,2,0) -> PCB 300kW inverter supply V1.5 | D5: 711526 | E5: =VLOOKUP(D5,'Malzeme Listesi'!A:C,2,0) -> PCB 300kW Inverter Supply V1.6
A6: 53571 | B6: =VLOOKUP(A6,[1]list!A:C,2,0) -> power contactor 230VAC 3RT1025-1AP00 | D6: 540548 | E6: =VLOOKUP(D6,'Malzeme Listesi'!A:C,2,0) -> contactor power- 230VAC 3RT2025-1AP00
A7: 53605 | B7: =VLOOKUP(A7,[1]list!A:C,2,0) -> switch temperature bimetal 70±4°C ma.re. | D7: 1072785 | E7: =VLOOKUP(D7,'Malzeme Listesi'!A:C,2,0) -> switch temperat.2455R Series Phenolic
A8: 53786 | B8: =VLOOKUP(A8,[1]list!A:C,2,0) -> PCB opt.distrib.contr.type CAN V2.2aE112 | D8: 759110 | E8: =VLOOKUP(D8,'Malzeme Listesi'!A:C,2,0) -> PCB CAN optical distribut. nacelle V2.4
A9: 66802 | B9: =VLOOKUP(A9,[1]list!A:C,2,0) -> PCB I/O board V1.5 E112 | D9: 692489 | E9: =VLOOKUP(D9,'Malzeme Listesi'!A:C,2,0) -> PCB I/O board V1.6 E112
A10: 56701 | B10: =VLOOKUP(A10,[1]list!A:C,2,0) -> heater fan 220-240VAC 250W HG Vario 250 | D10: 77188 | E10: =VLOOKUP(D10,'Malzeme Listesi'!A:C,2,0) -> heater fan 230V/250W ENERCON V2
A11: 78442 | B11: =VLOOKUP(A11,[1]list!A:C,2,0) -> PCB battery charger V2.4 E40 | D11: 574755 | E11: =VLOOKUP(D11,'Malzeme Listesi'!A:C,2,0) -> PCB battery charger V2.5 E40
A12: 79607 | B12: =VLOOKUP(A12,[1]list!A:C,2,0) -> slot closer E82 35,5X11,5X942MM t=0,48 | D12: 105581 | E12: =VLOOKUP(D12,'Malzeme Listesi'!A:C,2,0) -> E82 37,5X11,5X942MM t=0,53
A13: 94871 | B13: =VLOOKUP(A13,[1]list!A:C,2,0) -> magnetic coil 220VAC 18W ClassH | D13: 80796 | E13: =VLOOKUP(D13,'Malzeme Listesi'!A:C,2,0) -> hydraulic aggregate WILLMANN® 0512-06
A14: 82317 | B14: =VLOOKUP(A14,[1]list!A:C,2,0) -> Platine Controlboard Rectifier V1.4 E112 | D14: 695655 | E14: =VLOOKUP(D14,'Malzeme Listesi'!A:C,2,0) -> PCB Controlboard Rectifier V2.0 E112
... A16: 91660 | B16: =VLOOKUP(A16,[1]list!A:C,2,0) -> sensor noise KA1-Q25KB-DPÖ-X0485 | D16: 1007607 | E16: =VLOOKUP(D16,'Malzeme Listesi'!A:C,2,0) -> Sensor Noise 110dBA w.LEDdisplay 6,7m
A17: 91858 | B17: =VLOOKUP(A17,[1]list!A:C,2,0) -> groove brush f.generator round ø15mm | D17: tedarik edilemiyor | E17: =VLOOKUP(D17,'Malzeme Listesi'!A:C,2,0) -> #N/A
A18: 75161 | B18: =VLOOKUP(A18,[1]list!A:C,2,0) -> IGBT-module 1200V 145A SKM145GAL128D | D18: 98068 | E18: =VLOOKUP(D18,'Malzeme Listesi'!A:C,2,0) -> IGBT-module 1200V 150A SKM150GAL12T4
A19: 72334 | B19: =VLOOKUP(A19,[1]list!A:C,2,0) -> yaw motor with se ATB® MK40043-0 | D19: 103957 | E19: =VLOOKUP(D19,'Malzeme Listesi'!A:C,2,0) -> yaw motor with se +p ATB® MK40043-3
A20: 175643 | B20: =VLOOKUP(A20,[1]list!A:C,2,0) -> electrical filling pump f.clu Hove®vers2 | D20: 1069623 | E20: =VLOOKUP(D20,'Malzeme Listesi'!A:C,2,0) -> #N/A
A21: 112486 | B21: =VLOOKUP(A21,[1]list!A:C,2,0) -> grease cartridge 5Kg SHC460 pump Hove® | D21: 210475 | E21: =VLOOKUP(D21,'Malzeme Listesi'!A:C,2,0) -> grease cartridge 5Kg SHC461 WT pumpHove
A22: 585711 | B22: =VLOOKUP(A22,[1]list!A:C,2,0) -> rectifier block Proton T272-3200-18N | D22: 506809 | E22: =VLOOKUP(D22,'Malzeme Listesi'!A:C,2,0) -> rectifier block 2T3160N18TOF-KE02/...KTY
A23: 511910 | B23: =VLOOKUP(A23,[1]list!A:C,2,0) -> PCB controlboard pitch V2.1 | D23: 674129 | E23: =VLOOKUP(D23,'Malzeme Listesi'!A:C,2,0) -> PCB Controlboard Pitch CS48/82/101 V3.1
A24: 552656 | B24: =VLOOKUP(A24,[1]list!A:C,2,0) -> #N/A | D24: 512993 | E24: =VLOOKUP(D24,'Malzeme Listesi'!A:C,2,0) -> box capacitor rotor V2 ass. E48 Nesscap
A25: 75955 | B25: =VLOOKUP(A25,[1]list!A:C,2,0) -> capacitor 3300µF/450V B43564-S5338-M6 | D25: 542740 | E25: =VLOOKUP(D25,'Malzeme Listesi'!A:C,2,0) -> contactor power- 230VAC 3RT2026-1AP00
A26: 613363 | B26: =VLOOKUP(A26,[1]list!A:C,2,0) -> fan radial P9M-K0A40-SAB 7000m³/h | D26: 577352 | E26: =VLOOKUP(D26,'Malzeme Listesi'!A:C,2,0) -> radial fan GR56N-4DK.6N.AR
A27: 588947 | B27: =VLOOKUP(A27,[1]list!A:C,2,0) -> fan radial- 50Hz D2E146-AZ03-E7 | D27: 776279 | E27: =VLOOKUP(D27,'Malzeme Listesi'!A:C,2,0) -> fan 230V 50/60 Hz EBM D2E146AZ00XK +8mF
A28: 550332 | B28: =VLOOKUP(A28,[1]list!A:C,2,0) -> slip ring unit COBHAM V4 E48 w.att.w.h. | D28: 622129 | E28: =VLOOKUP(D28,'Malzeme Listesi'!A:C,2,0) -> slip ring unit COBHAM V6 E48 w.att.w.h
A29: 661267 | B29: =VLOOKUP(A29,[1]list!A:C,2,0) -> Console RM 17 Comfort DE | D29: 661270 | E29: =VLOOKUP(D29,'Malzeme Listesi'!A:C,2,0) -> #N/A
... A36: 96004 | B36: =VLOOKUP(A36,[1]list!A:C,2,0) -> sensor noise KA1-Q25KB-DPÖ-X0419 | D36: 1007605 | E36: =VLOOKUP(D36,'Malzeme Listesi'!A:C,2,0) -> Sensor acoustric 110dBA w.LEDdisplay 10m
